ast_names/__init__.py
ast_names/_main.py
ast_names/py.typed
ast_names-0.1.0.dist-info/LICENSE
ast_names-0.1.0.dist-info/METADATA
ast_names-0.1.0.dist-info/WHEEL
ast_names-0.1.0.dist-info/top_level.txt
ast_names-0.1.0.dist-info/RECORD
