Metadata-Version: 2.1
Name: ast-names
Version: 0.1.0
Summary: Collect top level variable names using the ast.
Home-page: https://github.com/tjsmart/ast_names
License: MIT
Classifier: License :: OSI Approved :: MIT License
Classifier: Programming Language :: Python :: 3
Classifier: Programming Language :: Python :: 3 :: Only
Classifier: Programming Language :: Python :: Implementation :: CPython
Requires-Python: >=3.8
License-File: LICENSE
